{
  "status": 0,
  "data": {
    "list": [{
      "id": "0001",
      "imgUrl": "/imgs/recommend/rem-1.jpg",
      "title": "故宫",
      "desc": "东方宫殿建筑代表，世界宫殿建筑典范"
    }, {
      "id": "0002",
      "imgUrl": "/imgs/recommend/rem-2.jpg",
      "title": "南山滑雪场",
      "desc": "北京专业级滑雪圣地"
    }, {
      "id": "0003",
      "imgUrl": "/imgs/recommend/rem-3.jpg",
      "title": "北京天安门",
      "desc": "我爱北京天安门，天安门上太阳升"
    }, {
      "id": "0004",
      "imgUrl": "/imgs/recommend/rem-4.jpg",
      "title": "水立方",
      "desc": "中国的荣耀，阳光下的晶莹水滴"
    }, {
      "id": "0005",
      "imgUrl": "/imgs/recommend/rem-5.jpg",
      "title": "温都水城养生馆",
      "desc": "各种亚热带植物掩映其间仿佛置身热带雨林"
    }]
  }
}


